{"ServiceDelivery": {"ResponseTimestamp": "2019-08-23T18:41:31Z", "ProducerRef": "SC", "Status": true, "StopMonitoringDelivery": {"version": "1.4", "ResponseTimestamp": "2019-08-23T18:41:31Z", "Status": true, "MonitoredStopVisit": [{"RecordedAtTime": "2019-08-23T18:41:21Z", "MonitoringRef": "60984", "MonitoredVehicleJourney": {"LineRef": "26", "DirectionRef": "West", "FramedVehicleJourneyRef": {"DataFrameRef": "2019-08-23", "DatedVehicleJourneyRef": "2640386"}, "PublishedLineName": "SUNNYVALE/LOCKHEED - EASTRIDGE", "OperatorRef": "SC", "OriginRef": "65807", "OriginName": "Eastridge Transit Center (Bay 9)", "DestinationRef": "60849", "DestinationName": "26 SUNNYVALE LOCKHEED", "Monitored": true, "InCongestion": null, "VehicleLocation": {"Longitude": "-121.861061", "Latitude": "37.3038597"}, "Bearing": null, "Occupancy": null, "VehicleRef": "7439", "MonitoredCall": {"StopPointRef": "60984", "StopPointName": "Campbell & Winchester", "VehicleLocationAtStop": "", "VehicleAtStop": "", "AimedArrivalTime": "2019-08-23T19:08:00Z", "ExpectedArrivalTime": "2019-08-23T19:08:00Z", "AimedDepartureTime": "2019-08-23T19:08:00Z", "ExpectedDepartureTime": "2019-08-23T19:08:00Z", "Distances": ""}}}, {"RecordedAtTime": "2019-08-23T18:41:21Z", "MonitoringRef": "60984", "MonitoredVehicleJourney": {"LineRef": "26", "DirectionRef": "West", "FramedVehicleJourneyRef": {"DataFrameRef": "2019-08-23", "DatedVehicleJourneyRef": "2640385"}, "PublishedLineName": "SUNNYVALE/LOCKHEED - EASTRIDGE", "OperatorRef": "SC", "OriginRef": "65807", "OriginName": "Eastridge Transit Center (Bay 9)", "DestinationRef": "60849", "DestinationName": "26 SUNNYVALE LOCKHEED", "Monitored": true, "InCongestion": null, "VehicleLocation": {"Longitude": "-121.81076", "Latitude": "37.3273087"}, "Bearing": null, "Occupancy": null, "VehicleRef": "2211", "MonitoredCall": {"StopPointRef": "60984", "StopPointName": "Campbell & Winchester", "VehicleLocationAtStop": "", "VehicleAtStop": "", "AimedArrivalTime": "2019-08-23T19:39:00Z", "ExpectedArrivalTime": "2019-08-23T19:39:00Z", "AimedDepartureTime": "2019-08-23T19:39:00Z", "ExpectedDepartureTime": "2019-08-23T19:39:00Z", "Distances": ""}}}, {"RecordedAtTime": "1970-01-01T00:00:00Z", "MonitoringRef": "60984", "MonitoredVehicleJourney": {"LineRef": "26", "DirectionRef": "West", "FramedVehicleJourneyRef": {"DataFrameRef": "2019-08-23", "DatedVehicleJourneyRef": "2640384"}, "PublishedLineName": "SUNNYVALE/LOCKHEED - EASTRIDGE", "OperatorRef": "SC", "OriginRef": "65807", "OriginName": "Eastridge Transit Center (Bay 9)", "DestinationRef": "60849", "DestinationName": "26 SUNNYVALE LOCKHEED", "Monitored": true, "InCongestion": null, "VehicleLocation": {"Longitude": "", "Latitude": ""}, "Bearing": null, "Occupancy": null, "VehicleRef": null, "MonitoredCall": {"StopPointRef": "60984", "StopPointName": "Campbell & Winchester", "VehicleLocationAtStop": "", "VehicleAtStop": "", "AimedArrivalTime": "2019-08-23T20:10:00Z", "ExpectedArrivalTime": "2019-08-23T20:10:00Z", "AimedDepartureTime": "2019-08-23T20:10:00Z", "ExpectedDepartureTime": "2019-08-23T20:10:00Z", "Distances": ""}}}]}}}